[
  {
    "title": "Psyk",
    "artist": "Techno",
    "plays": 1777,
    "market": "DE",
    "heat": 0.9
  },
  {
    "title": "Alan Fitzpatrick",
    "artist": "Tech House",
    "plays": 1881,
    "market": "GB",
    "heat": 0.9
  },
  {
    "title": "Adriatique",
    "artist": "Tech House",
    "plays": 1543,
    "market": "GB",
    "heat": 0.9
  },
  {
    "title": "Midland",
    "artist": "Deep House",
    "plays": 1740,
    "market": "US",
    "heat": 0.9
  },
  {
    "title": "Kasablanca",
    "artist": "Melodic Techno",
    "plays": 1719,
    "market": "IT",
    "heat": 0.9
  },
  {
    "title": "Tinlicker",
    "artist": "Melodic Techno",
    "plays": 1684,
    "market": "IT",
    "heat": 0.9
  },
  {
    "title": "RAFFA GUIDO",
    "artist": "Afro House",
    "plays": 1883,
    "market": "ZA",
    "heat": 0.9
  },
  {
    "title": "The Prophet",
    "artist": "Hard Techno",
    "plays": 1877,
    "market": "DE",
    "heat": 0.9
  },
  {
    "title": "thds",
    "artist": "Organic / Downtempo",
    "plays": 1939,
    "market": "CO",
    "heat": 0.9
  },
  {
    "title": "nbsplv",
    "artist": "Deep House",
    "plays": 1683,
    "market": "US",
    "heat": 0.9
  }
]